Metadata-Version: 1.1
Name: django-csv-exports
Version: 1.0.5
Summary: <Include a description of your project>
Home-page: https://github.com/victor-rocha/django-csv-exports
Author: Victor Rocha
Author-email: victor@rochapps.com
License: BSD
Platform: UNKNOWN
Classifier: Topic :: Internet :: WWW/HTTP :: Dynamic Content
Classifier: Intended Audience :: Developers
Classifier: Programming Language :: Python
Classifier: Programming Language :: Python :: 2.6
Classifier: Programming Language :: Python :: 2.7
Classifier: Framework :: Django
Classifier: Development Status :: 4 - Beta
Classifier: Operating System :: OS Independent
